ard_em.py
ard_em-0.1.4.dist-info/DESCRIPTION.rst
ard_em-0.1.4.dist-info/METADATA
ard_em-0.1.4.dist-info/RECORD
ard_em-0.1.4.dist-info/WHEEL
ard_em-0.1.4.dist-info/metadata.json
ard_em-0.1.4.dist-info/top_level.txt
