Metadata-Version: 2.0
Name: ard-em
Version: 0.1.4
Summary: ARD EM algorithm with automatic determination of components/clusters number
Home-page: https://github.com/Leensman/ard-em
Author: Artem Ryzhikov
Author-email: artemryzhikoff@yandex.ru
License: Apache-2.0 License
Keywords: pattern recognition,density reconstruction,cluster analysis,clusters number determination,EM algorithm,Bayes Learning,automatic relevance determination
Platform: UNKNOWN
Classifier: Development Status :: 5 - Production/Stable
Classifier: Intended Audience :: Science/Research
Classifier: License :: OSI Approved :: Apache Software License
Classifier: Programming Language :: Python :: 2.7 
Classifier: Programming Language :: Python :: 3.4 
Requires-Dist: scikit-learn (>=0.18.1)
